ezstructure/__init__.py
ezstructure/chooseK.py
ezstructure/distruct.py
ezstructure/fastStructure.cp311-win32.pyd
ezstructure/io.py
ezstructure/structure.py
ezstructure/vars/__init__.py
ezstructure/vars/admixprop.cp311-win32.pyd
ezstructure/vars/admixprop.h
ezstructure/vars/admixprop.pxd
ezstructure/vars/allelefreq.cp311-win32.pyd
ezstructure/vars/allelefreq.h
ezstructure/vars/allelefreq.pxd
ezstructure/vars/marglikehood.cp311-win32.pyd
ezstructure/vars/marglikehood.h
ezstructure/vars/utils.cp311-win32.pyd
ezstructure-1.0.4.dist-info/licenses/LICENSE
ezstructure-1.0.4.dist-info/METADATA
ezstructure-1.0.4.dist-info/WHEEL
ezstructure-1.0.4.dist-info/entry_points.txt
ezstructure-1.0.4.dist-info/top_level.txt
ezstructure-1.0.4.dist-info/RECORD
