Metadata-Version: 2.4
Name: ezstructure
Version: 1.0.4
Summary: EasyStructure
Author: Jerry Hoogenboom
Author-email: jerryhoogenboom@outlook.com
License: MIT
Project-URL: Bug Tracker, https://github.com/Jerrythafast/ezstructure/issues
Project-URL: Source Code, https://github.com/Jerrythafast/ezstructure
Keywords: bioinformatics forensics structure ancestry
Classifier: Programming Language :: Python :: 3
Classifier: Programming Language :: Cython
Classifier: Operating System :: OS Independent
Classifier: License :: OSI Approved :: MIT License
Classifier: Intended Audience :: Science/Research
Classifier: Intended Audience :: Legal Industry
Classifier: Topic :: Scientific/Engineering :: Bio-Informatics
Requires-Python: >=3.9
License-File: LICENSE
Requires-Dist: numpy<3,>=2
Requires-Dist: scipy
Dynamic: author
Dynamic: author-email
Dynamic: classifier
Dynamic: description
Dynamic: description-content-type
Dynamic: keywords
Dynamic: license
Dynamic: license-file
Dynamic: project-url
Dynamic: requires-dist
Dynamic: requires-python
Dynamic: summary
